{
    "title": "Launcher",
    "temp": true,
    "icon": "/packages/res/icons/launcher.png",
    "ui.property.style": {
        "left": "15%",
        "top": "15%",
        "width": "70%",
        "height": "70%"
    },
    "ui.basic.elements": [
        {
            "ui.basic.type": "search",
            "ui.attribute.placeholder": "Search",
            "ui.basic.text": "",
            "ui.class.classExtra": "app.launcher.search"
        },
        {
            "ui.basic.tag": "hr"
        },
        {
            "text": "Transform",
            "ui.basic.src": "/packages/res/icons/transform.png",
            "app.progman.args": "transform",
            "ui.touch.click": "core.app.transform"
        },
        {
            "text": "Player",
            "ui.basic.src": "/packages/res/icons/player.png",
            "app.progman.args": "player",
            "ui.touch.click": "core.app.player"
        }
    ]
}
